HoloLog/HoloLog.py
HoloLog/__init__.py
hololog-0.1.0.dist-info/METADATA
hololog-0.1.0.dist-info/WHEEL
hololog-0.1.0.dist-info/top_level.txt
hololog-0.1.0.dist-info/RECORD
