Metadata-Version: 2.4
Name: HoloLog
Version: 0.1.0
Summary: A modern way to auto log system errors
Author: Tristan McBride Sr.
Author-email: "Tristan McBride Sr." <142635792+TristanMcBrideSr@users.noreply.github.com>
Maintainer-email: "Tristan McBride Sr." <142635792+TristanMcBrideSr@users.noreply.github.com>
License-Expression: Apache-2.0
Project-URL: Homepage, https://github.com/TristanMcBrideSr
Keywords: Logging,Error Handling,System Monitoring,Python,loggers,error logging,system errors
Classifier: Programming Language :: Python :: 3
Classifier: Operating System :: OS Independent
Classifier: Intended Audience :: Developers
Requires-Python: >=3.10
Requires-Dist: python-dotenv
Requires-Dist: BitSig
Dynamic: author
